cookieLLMTest/__init__.py
cookieLLMTest/nlpbook/__init__.py
cookieLLMTest/nlpbook/data_utils.py
cookieLLMTest/nlpbook/metrics.py
cookieLLMTest/nlpbook/trainer.py
cookieLLMTest/nlpbook/utils.py
cookieLLMTest/nlpbook/classification/__init__.py
cookieLLMTest/nlpbook/classification/arguments.py
cookieLLMTest/nlpbook/classification/corpus.py
cookieLLMTest/nlpbook/classification/deploy.py
cookieLLMTest/nlpbook/classification/index.html
cookieLLMTest/nlpbook/classification/task.py
cookieLLMTest/nlpbook/generation/__init__.py
cookieLLMTest/nlpbook/generation/arguments.py
cookieLLMTest/nlpbook/generation/corpus.py
cookieLLMTest/nlpbook/generation/deploy.py
cookieLLMTest/nlpbook/generation/index.html
cookieLLMTest/nlpbook/generation/task.py
cookieLLMTest/nlpbook/ner/__init__.py
cookieLLMTest/nlpbook/ner/arguments.py
cookieLLMTest/nlpbook/ner/corpus.py
cookieLLMTest/nlpbook/ner/deploy.py
cookieLLMTest/nlpbook/ner/index.html
cookieLLMTest/nlpbook/ner/task.py
cookieLLMTest/nlpbook/paircls/__init__.py
cookieLLMTest/nlpbook/paircls/corpus.py
cookieLLMTest/nlpbook/paircls/deploy.py
cookieLLMTest/nlpbook/paircls/index.html
cookieLLMTest/nlpbook/qa/__init__.py
cookieLLMTest/nlpbook/qa/arguments.py
cookieLLMTest/nlpbook/qa/corpus.py
cookieLLMTest/nlpbook/qa/deploy.py
cookieLLMTest/nlpbook/qa/index.html
cookieLLMTest/nlpbook/qa/task.py
cookieLLMTest-1.0.6.dist-info/LICENSE
cookieLLMTest-1.0.6.dist-info/METADATA
cookieLLMTest-1.0.6.dist-info/WHEEL
cookieLLMTest-1.0.6.dist-info/top_level.txt
cookieLLMTest-1.0.6.dist-info/RECORD
