Metadata-Version: 2.1
Name: cookieLLMTest
Version: 1.0.6
Summary: LLM Processing test
Home-page: https://github.com/sjang01/cookieLLMTest
Author: sjang01
Author-email: sjang01@naver.com
License: MIT
Classifier: Programming Language :: Python :: 3.10
Classifier: License :: OSI Approved :: MIT License
Classifier: Operating System :: OS Independent
License-File: LICENSE
Requires-Dist: pytorch-lightning ==1.6.1
Requires-Dist: transformers ==4.28.1
Requires-Dist: Korpora >=0.2.0
Requires-Dist: flask >=1.1.4
Requires-Dist: flask-ngrok >=0.0.25
Requires-Dist: flask-cors >=3.0.10
